{"@id":"https://ky4meru.github.io/RedWine/registration/redwine.coercer/2.4.3.json","@type":["Package","http://schema.nuget.org/catalog#Permalink"],"catalogEntry":"https://ky4meru.github.io/RedWine/virtualcatalog/data/fe88d654-bfb8-494d-b0a0-8d450ad00307.json","listed":true,"packageContent":"https://ky4meru.github.io/RedWine/flatcontainer/redwine.coercer/2.4.3/redwine.coercer.2.4.3.nupkg","published":"2025-09-14T15:40:45.1660536Z","registration":"https://ky4meru.github.io/RedWine/registration/redwine.coercer/index.json","sleet:catalogEntry":{"@id":"https://ky4meru.github.io/RedWine/virtualcatalog/data/fe88d654-bfb8-494d-b0a0-8d450ad00307.json","@type":["PackageDetails","catalog:Permalink"],"authors":"@p0dalirius","commitId":"33ed480f-12e2-41ed-a32b-14ffcba90466","commitTimeStamp":"2025-09-14T15:40:45.1661235Z","copyright":"","created":"2025-09-14T15:40:45.1660536Z","description":"A python script to automatically coerce a Windows server to authenticate on an arbitrary machine through 12 methods","iconUrl":"","id":"redwine.coercer","isPrerelease":false,"language":"","lastEdited":"0001-01-01T00:00:00Z","licenseNames":"","licenseReportUrl":"","licenseUrl":"","listed":true,"owners":"","packageContent":"https://ky4meru.github.io/RedWine/flatcontainer/redwine.coercer/2.4.3/redwine.coercer.2.4.3.nupkg","projectUrl":"https://github.com/p0dalirius/Coercer","published":"2025-09-14T15:40:45.1660536Z","releaseNotes":"","requireLicenseAcceptance":false,"sleet:operation":"add","sleet:toolVersion":"6.5.13","summary":"","title":"Coercer","version":"2.4.3","dependencyGroups":[{"@id":"https://ky4meru.github.io/RedWine/virtualcatalog/data/fe88d654-bfb8-494d-b0a0-8d450ad00307.json#dependencygroup/any","@type":"PackageDependencyGroup","dependencies":[{"@id":"https://ky4meru.github.io/RedWine/virtualcatalog/data/fe88d654-bfb8-494d-b0a0-8d450ad00307.json#dependencygroup/any/redwine.pipx","@type":"PackageDependency","id":"redwine.pipx","range":"(, )"}]}],"frameworkAssemblyGroup":[],"tags":[],"@context":{"@vocab":"http://schema.nuget.org/schema#","catalog":"http://schema.nuget.org/catalog#","xsd":"http://www.w3.org/2001/XMLSchema#","sleet":"http://schema.emgarten.com/sleet#","dependencies":{"@id":"dependency","@container":"@set"},"dependencyGroups":{"@id":"dependencyGroup","@container":"@set"},"packageEntries":{"@id":"packageEntry","@container":"@set"},"supportedFrameworks":{"@id":"supportedFramework","@container":"@set"},"tags":{"@id":"tag","@container":"@set"},"published":{"@type":"xsd:dateTime"},"created":{"@type":"xsd:dateTime"},"lastEdited":{"@type":"xsd:dateTime"},"catalog:commitTimeStamp":{"@type":"xsd:dateTime"}}},"@context":{"@vocab":"http://schema.nuget.org/schema#","catalog":"http://schema.nuget.org/catalog#","xsd":"http://www.w3.org/2001/XMLSchema#","sleet":"http://schema.emgarten.com/sleet#","catalogEntry":{"@type":"@id"},"registration":{"@type":"@id"},"packageContent":{"@type":"@id"},"published":{"@type":"xsd:dateTime"},"dependencies":{"@id":"dependency","@container":"@set"},"dependencyGroups":{"@id":"dependencyGroup","@container":"@set"},"packageEntries":{"@id":"packageEntry","@container":"@set"},"supportedFrameworks":{"@id":"supportedFramework","@container":"@set"},"tags":{"@id":"tag","@container":"@set"},"created":{"@type":"xsd:dateTime"},"lastEdited":{"@type":"xsd:dateTime"},"catalog:commitTimeStamp":{"@type":"xsd:dateTime"}}}