{"@id":"https://ky4meru.github.io/RedWine/registration/redwine.invoke-obfuscation/1.1.0.json","@type":["Package","http://schema.nuget.org/catalog#Permalink"],"catalogEntry":"https://ky4meru.github.io/RedWine/virtualcatalog/data/cf42e112-01d5-4979-b7a0-f0facc0c2cab.json","listed":true,"packageContent":"https://ky4meru.github.io/RedWine/flatcontainer/redwine.invoke-obfuscation/1.1.0/redwine.invoke-obfuscation.1.1.0.nupkg","published":"2025-09-15T10:11:14.1866567Z","registration":"https://ky4meru.github.io/RedWine/registration/redwine.invoke-obfuscation/index.json","sleet:catalogEntry":{"@id":"https://ky4meru.github.io/RedWine/virtualcatalog/data/cf42e112-01d5-4979-b7a0-f0facc0c2cab.json","@type":["PackageDetails","catalog:Permalink"],"authors":"@danielbohannon","commitId":"b8bc3a37-2f28-4421-8828-3ce7a6f1f4cf","commitTimeStamp":"2025-09-15T10:11:14.1867196Z","copyright":"","created":"2025-09-15T10:11:14.1866567Z","description":"PowerShell Obfuscator","iconUrl":"","id":"redwine.invoke-obfuscation","isPrerelease":false,"language":"","lastEdited":"0001-01-01T00:00:00Z","licenseNames":"","licenseReportUrl":"","licenseUrl":"","listed":true,"owners":"","packageContent":"https://ky4meru.github.io/RedWine/flatcontainer/redwine.invoke-obfuscation/1.1.0/redwine.invoke-obfuscation.1.1.0.nupkg","projectUrl":"https://github.com/danielbohannon/Invoke-Obfuscation","published":"2025-09-15T10:11:14.1866567Z","releaseNotes":"","requireLicenseAcceptance":false,"sleet:operation":"add","sleet:toolVersion":"6.5.13","summary":"","title":"Invoke-Obfuscation","version":"1.1.0","dependencyGroups":[],"frameworkAssemblyGroup":[],"tags":[],"@context":{"@vocab":"http://schema.nuget.org/schema#","catalog":"http://schema.nuget.org/catalog#","xsd":"http://www.w3.org/2001/XMLSchema#","sleet":"http://schema.emgarten.com/sleet#","dependencies":{"@id":"dependency","@container":"@set"},"dependencyGroups":{"@id":"dependencyGroup","@container":"@set"},"packageEntries":{"@id":"packageEntry","@container":"@set"},"supportedFrameworks":{"@id":"supportedFramework","@container":"@set"},"tags":{"@id":"tag","@container":"@set"},"published":{"@type":"xsd:dateTime"},"created":{"@type":"xsd:dateTime"},"lastEdited":{"@type":"xsd:dateTime"},"catalog:commitTimeStamp":{"@type":"xsd:dateTime"}}},"@context":{"@vocab":"http://schema.nuget.org/schema#","catalog":"http://schema.nuget.org/catalog#","xsd":"http://www.w3.org/2001/XMLSchema#","sleet":"http://schema.emgarten.com/sleet#","catalogEntry":{"@type":"@id"},"registration":{"@type":"@id"},"packageContent":{"@type":"@id"},"published":{"@type":"xsd:dateTime"},"dependencies":{"@id":"dependency","@container":"@set"},"dependencyGroups":{"@id":"dependencyGroup","@container":"@set"},"packageEntries":{"@id":"packageEntry","@container":"@set"},"supportedFrameworks":{"@id":"supportedFramework","@container":"@set"},"tags":{"@id":"tag","@container":"@set"},"created":{"@type":"xsd:dateTime"},"lastEdited":{"@type":"xsd:dateTime"},"catalog:commitTimeStamp":{"@type":"xsd:dateTime"}}}