{"@id":"https://ky4meru.github.io/RedWine/registration/redwine.powerupsql/index.json","@type":["catalog:CatalogRoot","PackageRegistration","catalog:Permalink"],"commitId":"c8ae25cf-3c8c-418e-8b16-d7af11dacb78","commitTimeStamp":"2025-09-15T11:41:49.2033796Z","count":1,"items":[{"@id":"https://ky4meru.github.io/RedWine/registration/redwine.powerupsql/index.json#page/1.0.0/1.0.0","@type":"catalog:CatalogPage","commitId":"c8ae25cf-3c8c-418e-8b16-d7af11dacb78","commitTimeStamp":"2025-09-15T11:41:49.2035519Z","count":1,"lower":"1.0.0","parent":"https://ky4meru.github.io/RedWine/registration/redwine.powerupsql/index.json","upper":"1.0.0","items":[{"@id":"https://ky4meru.github.io/RedWine/registration/redwine.powerupsql/1.0.0.json","@type":"Package","catalogEntry":{"@id":"https://ky4meru.github.io/RedWine/virtualcatalog/data/5df12a53-92e1-4389-abad-3ff02fd4ccc8.json","@type":["PackageDetails","catalog:Permalink"],"authors":"@NetSPI","dependencyGroups":[],"description":"A PowerShell Toolkit for Attacking SQL Server","iconUrl":"","id":"redwine.powerupsql","language":"","licenseUrl":"","listed":true,"packageContent":"https://ky4meru.github.io/RedWine/flatcontainer/redwine.powerupsql/1.0.0/redwine.powerupsql.1.0.0.nupkg","projectUrl":"https://github.com/NetSPI/PowerUpSQL","published":"2025-09-15T11:41:49.0898334Z","requireLicenseAcceptance":false,"summary":"","tags":[],"title":"PowerUpSQL","version":"1.0.0"},"commitId":"c8ae25cf-3c8c-418e-8b16-d7af11dacb78","commitTimeStamp":"2025-09-15T11:41:49.2032429Z","packageContent":"https://ky4meru.github.io/RedWine/flatcontainer/redwine.powerupsql/1.0.0/redwine.powerupsql.1.0.0.nupkg","registration":"https://ky4meru.github.io/RedWine/registration/redwine.powerupsql/index.json"}]}],"@context":{"@vocab":"http://schema.nuget.org/schema#","catalog":"http://schema.nuget.org/catalog#","xsd":"http://www.w3.org/2001/XMLSchema#","sleet":"http://schema.emgarten.com/sleet#","items":{"@id":"catalog:item","@container":"@set"},"commitTimeStamp":{"@id":"catalog:commitTimeStamp","@type":"xsd:dateTime"},"commitId":{"@id":"catalog:commitId"},"count":{"@id":"catalog:count"},"parent":{"@id":"catalog:parent","@type":"@id"},"tags":{"@container":"@set","@id":"tag"},"packageTargetFrameworks":{"@container":"@set","@id":"packageTargetFramework"},"dependencyGroups":{"@container":"@set","@id":"dependencyGroup"},"dependencies":{"@container":"@set","@id":"dependency"},"packageContent":{"@type":"@id"},"published":{"@type":"xsd:dateTime"},"registration":{"@type":"@id"}}}