{"@id":"https://ky4meru.github.io/RedWine/registration/redwine.azurehound/index.json","@type":["catalog:CatalogRoot","PackageRegistration","catalog:Permalink"],"commitId":"cfb972f2-6607-499b-97b4-6a329c4f6a7e","commitTimeStamp":"2025-09-14T17:44:48.4184966Z","count":1,"items":[{"@id":"https://ky4meru.github.io/RedWine/registration/redwine.azurehound/index.json#page/2.7.1/2.7.1","@type":"catalog:CatalogPage","commitId":"cfb972f2-6607-499b-97b4-6a329c4f6a7e","commitTimeStamp":"2025-09-14T17:44:48.4186561Z","count":1,"lower":"2.7.1","parent":"https://ky4meru.github.io/RedWine/registration/redwine.azurehound/index.json","upper":"2.7.1","items":[{"@id":"https://ky4meru.github.io/RedWine/registration/redwine.azurehound/2.7.1.json","@type":"Package","catalogEntry":{"@id":"https://ky4meru.github.io/RedWine/virtualcatalog/data/049fb019-2a65-4a11-bc03-04062519571d.json","@type":["PackageDetails","catalog:Permalink"],"authors":"@SpecterOps","dependencyGroups":[],"description":"Azure Data Exporter for BloodHound","iconUrl":"","id":"redwine.azurehound","language":"","licenseUrl":"","listed":true,"packageContent":"https://ky4meru.github.io/RedWine/flatcontainer/redwine.azurehound/2.7.1/redwine.azurehound.2.7.1.nupkg","projectUrl":"https://github.com/SpecterOps/AzureHound","published":"2025-09-14T17:44:48.3060532Z","requireLicenseAcceptance":false,"summary":"","tags":[],"title":"AzureHound","version":"2.7.1"},"commitId":"cfb972f2-6607-499b-97b4-6a329c4f6a7e","commitTimeStamp":"2025-09-14T17:44:48.4183343Z","packageContent":"https://ky4meru.github.io/RedWine/flatcontainer/redwine.azurehound/2.7.1/redwine.azurehound.2.7.1.nupkg","registration":"https://ky4meru.github.io/RedWine/registration/redwine.azurehound/index.json"}]}],"@context":{"@vocab":"http://schema.nuget.org/schema#","catalog":"http://schema.nuget.org/catalog#","xsd":"http://www.w3.org/2001/XMLSchema#","sleet":"http://schema.emgarten.com/sleet#","items":{"@id":"catalog:item","@container":"@set"},"commitTimeStamp":{"@id":"catalog:commitTimeStamp","@type":"xsd:dateTime"},"commitId":{"@id":"catalog:commitId"},"count":{"@id":"catalog:count"},"parent":{"@id":"catalog:parent","@type":"@id"},"tags":{"@container":"@set","@id":"tag"},"packageTargetFrameworks":{"@container":"@set","@id":"packageTargetFramework"},"dependencyGroups":{"@container":"@set","@id":"dependencyGroup"},"dependencies":{"@container":"@set","@id":"dependency"},"packageContent":{"@type":"@id"},"published":{"@type":"xsd:dateTime"},"registration":{"@type":"@id"}}}