{"@id":"https://ky4meru.github.io/RedWine/registration/redwine.winpwn/index.json","@type":["catalog:CatalogRoot","PackageRegistration","catalog:Permalink"],"commitId":"2035a6e0-9aac-4726-8149-85f21ffb8ca1","commitTimeStamp":"2025-09-14T07:56:08.3252424Z","count":1,"items":[{"@id":"https://ky4meru.github.io/RedWine/registration/redwine.winpwn/index.json#page/1.6.0/1.6.0","@type":"catalog:CatalogPage","commitId":"2035a6e0-9aac-4726-8149-85f21ffb8ca1","commitTimeStamp":"2025-09-14T07:56:08.3254041Z","count":1,"lower":"1.6.0","parent":"https://ky4meru.github.io/RedWine/registration/redwine.winpwn/index.json","upper":"1.6.0","items":[{"@id":"https://ky4meru.github.io/RedWine/registration/redwine.winpwn/1.6.0.json","@type":"Package","catalogEntry":{"@id":"https://ky4meru.github.io/RedWine/virtualcatalog/data/ab8150ac-f852-4e06-a8c0-5f4f26d66ff3.json","@type":["PackageDetails","catalog:Permalink"],"authors":"@S3cur3Th1sSh1t","dependencyGroups":[],"description":"Automation for internal Windows Penetrationtest / AD-Security","iconUrl":"","id":"redwine.winpwn","language":"","licenseUrl":"","listed":true,"packageContent":"https://ky4meru.github.io/RedWine/flatcontainer/redwine.winpwn/1.6.0/redwine.winpwn.1.6.0.nupkg","projectUrl":"https://github.com/S3cur3Th1sSh1t/WinPwn","published":"2025-09-14T07:56:08.2137569Z","requireLicenseAcceptance":false,"summary":"","tags":[],"title":"WinPwn","version":"1.6.0"},"commitId":"2035a6e0-9aac-4726-8149-85f21ffb8ca1","commitTimeStamp":"2025-09-14T07:56:08.3250889Z","packageContent":"https://ky4meru.github.io/RedWine/flatcontainer/redwine.winpwn/1.6.0/redwine.winpwn.1.6.0.nupkg","registration":"https://ky4meru.github.io/RedWine/registration/redwine.winpwn/index.json"}]}],"@context":{"@vocab":"http://schema.nuget.org/schema#","catalog":"http://schema.nuget.org/catalog#","xsd":"http://www.w3.org/2001/XMLSchema#","sleet":"http://schema.emgarten.com/sleet#","items":{"@id":"catalog:item","@container":"@set"},"commitTimeStamp":{"@id":"catalog:commitTimeStamp","@type":"xsd:dateTime"},"commitId":{"@id":"catalog:commitId"},"count":{"@id":"catalog:count"},"parent":{"@id":"catalog:parent","@type":"@id"},"tags":{"@container":"@set","@id":"tag"},"packageTargetFrameworks":{"@container":"@set","@id":"packageTargetFramework"},"dependencyGroups":{"@container":"@set","@id":"dependencyGroup"},"dependencies":{"@container":"@set","@id":"dependency"},"packageContent":{"@type":"@id"},"published":{"@type":"xsd:dateTime"},"registration":{"@type":"@id"}}}