{"@id":"https://ky4meru.github.io/RedWine/registration/msolspray/index.json","@type":["catalog:CatalogRoot","PackageRegistration","catalog:Permalink"],"commitId":"1943c543-adb1-4800-9914-844bf026ee0f","commitTimeStamp":"2025-09-03T10:44:20.0887471Z","count":1,"items":[{"@id":"https://ky4meru.github.io/RedWine/registration/msolspray/index.json#page/1.0.0/1.0.0","@type":"catalog:CatalogPage","commitId":"1943c543-adb1-4800-9914-844bf026ee0f","commitTimeStamp":"2025-09-03T10:44:20.0887724Z","count":1,"lower":"1.0.0","parent":"https://ky4meru.github.io/RedWine/registration/msolspray/index.json","upper":"1.0.0","items":[{"@id":"https://ky4meru.github.io/RedWine/registration/msolspray/1.0.0.json","@type":"Package","catalogEntry":{"@id":"https://ky4meru.github.io/RedWine/virtualcatalog/data/300a2fb9-770c-4926-a022-7a6c185eab90.json","@type":["PackageDetails","catalog:Permalink"],"authors":"@dafthack","dependencyGroups":[],"description":"A password spraying tool for Microsoft Online accounts (Azure/O365)","iconUrl":"","id":"msolspray","language":"","licenseUrl":"","listed":true,"packageContent":"https://ky4meru.github.io/RedWine/flatcontainer/msolspray/1.0.0/msolspray.1.0.0.nupkg","projectUrl":"https://github.com/dafthack/MSOLSpray","published":"2025-09-03T10:44:20.0443605Z","requireLicenseAcceptance":false,"summary":"","tags":[],"title":"MSOLSpray","version":"1.0.0"},"commitId":"1943c543-adb1-4800-9914-844bf026ee0f","commitTimeStamp":"2025-09-03T10:44:20.0886754Z","packageContent":"https://ky4meru.github.io/RedWine/flatcontainer/msolspray/1.0.0/msolspray.1.0.0.nupkg","registration":"https://ky4meru.github.io/RedWine/registration/msolspray/index.json"}]}],"@context":{"@vocab":"http://schema.nuget.org/schema#","catalog":"http://schema.nuget.org/catalog#","xsd":"http://www.w3.org/2001/XMLSchema#","sleet":"http://schema.emgarten.com/sleet#","items":{"@id":"catalog:item","@container":"@set"},"commitTimeStamp":{"@id":"catalog:commitTimeStamp","@type":"xsd:dateTime"},"commitId":{"@id":"catalog:commitId"},"count":{"@id":"catalog:count"},"parent":{"@id":"catalog:parent","@type":"@id"},"tags":{"@container":"@set","@id":"tag"},"packageTargetFrameworks":{"@container":"@set","@id":"packageTargetFramework"},"dependencyGroups":{"@container":"@set","@id":"dependencyGroup"},"dependencies":{"@container":"@set","@id":"dependency"},"packageContent":{"@type":"@id"},"published":{"@type":"xsd:dateTime"},"registration":{"@type":"@id"}}}