{"@id":"https://ky4meru.github.io/RedWine/registration/safetykatz/index.json","@type":["catalog:CatalogRoot","PackageRegistration","catalog:Permalink"],"commitId":"5be55f74-d78e-40ca-885e-5ffe93a656a8","commitTimeStamp":"2025-09-05T12:46:53.1097809Z","count":1,"items":[{"@id":"https://ky4meru.github.io/RedWine/registration/safetykatz/index.json#page/1.0.0/1.0.0","@type":"catalog:CatalogPage","commitId":"5be55f74-d78e-40ca-885e-5ffe93a656a8","commitTimeStamp":"2025-09-05T12:46:53.1099361Z","count":1,"lower":"1.0.0","parent":"https://ky4meru.github.io/RedWine/registration/safetykatz/index.json","upper":"1.0.0","items":[{"@id":"https://ky4meru.github.io/RedWine/registration/safetykatz/1.0.0.json","@type":"Package","catalogEntry":{"@id":"https://ky4meru.github.io/RedWine/virtualcatalog/data/a69d4668-0003-4600-85de-c319f5da35b1.json","@type":["PackageDetails","catalog:Permalink"],"authors":"@GhostPack","dependencyGroups":[{"@id":"https://ky4meru.github.io/RedWine/virtualcatalog/data/a69d4668-0003-4600-85de-c319f5da35b1.json#dependencygroup/any","@type":"PackageDependencyGroup","dependencies":[{"@id":"https://ky4meru.github.io/RedWine/virtualcatalog/data/a69d4668-0003-4600-85de-c319f5da35b1.json#dependencygroup/any/dotnet-frameworks","@type":"PackageDependency","id":"dotnet-frameworks","range":"(, )"}]}],"description":"SafetyKatz is a combination of slightly modified version of @gentilkiwi's Mimikatz project and @subTee's .NET PE Loader","iconUrl":"","id":"safetykatz","language":"","licenseUrl":"","listed":true,"packageContent":"https://ky4meru.github.io/RedWine/flatcontainer/safetykatz/1.0.0/safetykatz.1.0.0.nupkg","projectUrl":"https://github.com/GhostPack/SafetyKatz","published":"2025-09-05T12:46:52.9976647Z","requireLicenseAcceptance":false,"summary":"","tags":[],"title":"SafetyKatz","version":"1.0.0"},"commitId":"5be55f74-d78e-40ca-885e-5ffe93a656a8","commitTimeStamp":"2025-09-05T12:46:53.1096214Z","packageContent":"https://ky4meru.github.io/RedWine/flatcontainer/safetykatz/1.0.0/safetykatz.1.0.0.nupkg","registration":"https://ky4meru.github.io/RedWine/registration/safetykatz/index.json"}]}],"@context":{"@vocab":"http://schema.nuget.org/schema#","catalog":"http://schema.nuget.org/catalog#","xsd":"http://www.w3.org/2001/XMLSchema#","sleet":"http://schema.emgarten.com/sleet#","items":{"@id":"catalog:item","@container":"@set"},"commitTimeStamp":{"@id":"catalog:commitTimeStamp","@type":"xsd:dateTime"},"commitId":{"@id":"catalog:commitId"},"count":{"@id":"catalog:count"},"parent":{"@id":"catalog:parent","@type":"@id"},"tags":{"@container":"@set","@id":"tag"},"packageTargetFrameworks":{"@container":"@set","@id":"packageTargetFramework"},"dependencyGroups":{"@container":"@set","@id":"dependencyGroup"},"dependencies":{"@container":"@set","@id":"dependency"},"packageContent":{"@type":"@id"},"published":{"@type":"xsd:dateTime"},"registration":{"@type":"@id"}}}