{"@id":"https://ky4meru.github.io/RedWine/registration/whisker/1.0.0.json","@type":["Package","http://schema.nuget.org/catalog#Permalink"],"catalogEntry":"https://ky4meru.github.io/RedWine/virtualcatalog/data/88ac3981-d226-4bb3-b523-cb09974dd6cd.json","listed":true,"packageContent":"https://ky4meru.github.io/RedWine/flatcontainer/whisker/1.0.0/whisker.1.0.0.nupkg","published":"2025-09-10T10:46:49.8587350Z","registration":"https://ky4meru.github.io/RedWine/registration/whisker/index.json","sleet:catalogEntry":{"@id":"https://ky4meru.github.io/RedWine/virtualcatalog/data/88ac3981-d226-4bb3-b523-cb09974dd6cd.json","@type":["PackageDetails","catalog:Permalink"],"authors":"@eladshamir","commitId":"e8454462-6177-420e-89ad-ed995cd9939d","commitTimeStamp":"2025-09-10T10:46:49.8587910Z","copyright":"","created":"2025-09-10T10:46:49.8587350Z","description":"Whisker is a C# tool for taking over Active Directory user and computer accounts by manipulating their msDS-KeyCredentialLink attribute, effectively adding \"Shadow Credentials\" to the target account","iconUrl":"","id":"whisker","isPrerelease":false,"language":"","lastEdited":"0001-01-01T00:00:00Z","licenseNames":"","licenseReportUrl":"","licenseUrl":"","listed":true,"owners":"","packageContent":"https://ky4meru.github.io/RedWine/flatcontainer/whisker/1.0.0/whisker.1.0.0.nupkg","projectUrl":"https://github.com/eladshamir/Whisker","published":"2025-09-10T10:46:49.8587350Z","releaseNotes":"","requireLicenseAcceptance":false,"sleet:operation":"add","sleet:toolVersion":"6.5.13","summary":"","title":"Whisker","version":"1.0.0","dependencyGroups":[{"@id":"https://ky4meru.github.io/RedWine/virtualcatalog/data/88ac3981-d226-4bb3-b523-cb09974dd6cd.json#dependencygroup/any","@type":"PackageDependencyGroup","dependencies":[{"@id":"https://ky4meru.github.io/RedWine/virtualcatalog/data/88ac3981-d226-4bb3-b523-cb09974dd6cd.json#dependencygroup/any/dotnet-frameworks","@type":"PackageDependency","id":"dotnet-frameworks","range":"(, )"}]}],"frameworkAssemblyGroup":[],"tags":[],"@context":{"@vocab":"http://schema.nuget.org/schema#","catalog":"http://schema.nuget.org/catalog#","xsd":"http://www.w3.org/2001/XMLSchema#","sleet":"http://schema.emgarten.com/sleet#","dependencies":{"@id":"dependency","@container":"@set"},"dependencyGroups":{"@id":"dependencyGroup","@container":"@set"},"packageEntries":{"@id":"packageEntry","@container":"@set"},"supportedFrameworks":{"@id":"supportedFramework","@container":"@set"},"tags":{"@id":"tag","@container":"@set"},"published":{"@type":"xsd:dateTime"},"created":{"@type":"xsd:dateTime"},"lastEdited":{"@type":"xsd:dateTime"},"catalog:commitTimeStamp":{"@type":"xsd:dateTime"}}},"@context":{"@vocab":"http://schema.nuget.org/schema#","catalog":"http://schema.nuget.org/catalog#","xsd":"http://www.w3.org/2001/XMLSchema#","sleet":"http://schema.emgarten.com/sleet#","catalogEntry":{"@type":"@id"},"registration":{"@type":"@id"},"packageContent":{"@type":"@id"},"published":{"@type":"xsd:dateTime"},"dependencies":{"@id":"dependency","@container":"@set"},"dependencyGroups":{"@id":"dependencyGroup","@container":"@set"},"packageEntries":{"@id":"packageEntry","@container":"@set"},"supportedFrameworks":{"@id":"supportedFramework","@container":"@set"},"tags":{"@id":"tag","@container":"@set"},"created":{"@type":"xsd:dateTime"},"lastEdited":{"@type":"xsd:dateTime"},"catalog:commitTimeStamp":{"@type":"xsd:dateTime"}}}