{"@id":"https://ky4meru.github.io/RedWine/registration/redwine.kerbrute/index.json","@type":["catalog:CatalogRoot","PackageRegistration","catalog:Permalink"],"commitId":"bf105907-c3e6-4542-84bc-4011ab3d274a","commitTimeStamp":"2025-09-13T19:52:28.9425274Z","count":1,"items":[{"@id":"https://ky4meru.github.io/RedWine/registration/redwine.kerbrute/index.json#page/1.0.3/1.0.3","@type":"catalog:CatalogPage","commitId":"bf105907-c3e6-4542-84bc-4011ab3d274a","commitTimeStamp":"2025-09-13T19:52:28.9426891Z","count":1,"lower":"1.0.3","parent":"https://ky4meru.github.io/RedWine/registration/redwine.kerbrute/index.json","upper":"1.0.3","items":[{"@id":"https://ky4meru.github.io/RedWine/registration/redwine.kerbrute/1.0.3.json","@type":"Package","catalogEntry":{"@id":"https://ky4meru.github.io/RedWine/virtualcatalog/data/202dc39d-e0e6-4507-8e08-b2e8bd02603e.json","@type":["PackageDetails","catalog:Permalink"],"authors":"@ropnop","dependencyGroups":[],"description":"A tool to perform Kerberos pre-auth bruteforcing","iconUrl":"","id":"redwine.kerbrute","language":"","licenseUrl":"","listed":true,"packageContent":"https://ky4meru.github.io/RedWine/flatcontainer/redwine.kerbrute/1.0.3/redwine.kerbrute.1.0.3.nupkg","projectUrl":"https://github.com/ropnop/kerbrute","published":"2025-09-13T19:52:28.8333413Z","requireLicenseAcceptance":false,"summary":"","tags":[],"title":"Kerbrute","version":"1.0.3"},"commitId":"bf105907-c3e6-4542-84bc-4011ab3d274a","commitTimeStamp":"2025-09-13T19:52:28.9423726Z","packageContent":"https://ky4meru.github.io/RedWine/flatcontainer/redwine.kerbrute/1.0.3/redwine.kerbrute.1.0.3.nupkg","registration":"https://ky4meru.github.io/RedWine/registration/redwine.kerbrute/index.json"}]}],"@context":{"@vocab":"http://schema.nuget.org/schema#","catalog":"http://schema.nuget.org/catalog#","xsd":"http://www.w3.org/2001/XMLSchema#","sleet":"http://schema.emgarten.com/sleet#","items":{"@id":"catalog:item","@container":"@set"},"commitTimeStamp":{"@id":"catalog:commitTimeStamp","@type":"xsd:dateTime"},"commitId":{"@id":"catalog:commitId"},"count":{"@id":"catalog:count"},"parent":{"@id":"catalog:parent","@type":"@id"},"tags":{"@container":"@set","@id":"tag"},"packageTargetFrameworks":{"@container":"@set","@id":"packageTargetFramework"},"dependencyGroups":{"@container":"@set","@id":"dependencyGroup"},"dependencies":{"@container":"@set","@id":"dependency"},"packageContent":{"@type":"@id"},"published":{"@type":"xsd:dateTime"},"registration":{"@type":"@id"}}}