{"@id":"https://ky4meru.github.io/RedWine/registration/gowitness/index.json","@type":["catalog:CatalogRoot","PackageRegistration","catalog:Permalink"],"commitId":"1d4a2563-c60b-41ab-8d51-d07686f6e8ec","commitTimeStamp":"2025-09-05T12:46:41.4732057Z","count":1,"items":[{"@id":"https://ky4meru.github.io/RedWine/registration/gowitness/index.json#page/3.0.5/3.0.5","@type":"catalog:CatalogPage","commitId":"1d4a2563-c60b-41ab-8d51-d07686f6e8ec","commitTimeStamp":"2025-09-05T12:46:41.4733824Z","count":1,"lower":"3.0.5","parent":"https://ky4meru.github.io/RedWine/registration/gowitness/index.json","upper":"3.0.5","items":[{"@id":"https://ky4meru.github.io/RedWine/registration/gowitness/3.0.5.json","@type":"Package","catalogEntry":{"@id":"https://ky4meru.github.io/RedWine/virtualcatalog/data/040b7e09-3098-4941-b7f9-62f2ab33c454.json","@type":["PackageDetails","catalog:Permalink"],"authors":"@sensepost","dependencyGroups":[],"description":"A golang, web screenshot utility using Chrome Headless","iconUrl":"","id":"gowitness","language":"","licenseUrl":"","listed":true,"packageContent":"https://ky4meru.github.io/RedWine/flatcontainer/gowitness/3.0.5/gowitness.3.0.5.nupkg","projectUrl":"https://github.com/sensepost/gowitness","published":"2025-09-05T12:46:41.3626569Z","requireLicenseAcceptance":false,"summary":"","tags":[],"title":"Gowitness","version":"3.0.5"},"commitId":"1d4a2563-c60b-41ab-8d51-d07686f6e8ec","commitTimeStamp":"2025-09-05T12:46:41.4730556Z","packageContent":"https://ky4meru.github.io/RedWine/flatcontainer/gowitness/3.0.5/gowitness.3.0.5.nupkg","registration":"https://ky4meru.github.io/RedWine/registration/gowitness/index.json"}]}],"@context":{"@vocab":"http://schema.nuget.org/schema#","catalog":"http://schema.nuget.org/catalog#","xsd":"http://www.w3.org/2001/XMLSchema#","sleet":"http://schema.emgarten.com/sleet#","items":{"@id":"catalog:item","@container":"@set"},"commitTimeStamp":{"@id":"catalog:commitTimeStamp","@type":"xsd:dateTime"},"commitId":{"@id":"catalog:commitId"},"count":{"@id":"catalog:count"},"parent":{"@id":"catalog:parent","@type":"@id"},"tags":{"@container":"@set","@id":"tag"},"packageTargetFrameworks":{"@container":"@set","@id":"packageTargetFramework"},"dependencyGroups":{"@container":"@set","@id":"dependencyGroup"},"dependencies":{"@container":"@set","@id":"dependency"},"packageContent":{"@type":"@id"},"published":{"@type":"xsd:dateTime"},"registration":{"@type":"@id"}}}