{"@id":"https://ky4meru.github.io/RedWine/registration/windows-update/index.json","@type":["catalog:CatalogRoot","PackageRegistration","catalog:Permalink"],"commitId":"57e3cd3c-1bfd-447b-bb06-3bca889d3a9f","commitTimeStamp":"2025-09-05T12:47:02.4664584Z","count":1,"items":[{"@id":"https://ky4meru.github.io/RedWine/registration/windows-update/index.json#page/1.0.0/1.0.0","@type":"catalog:CatalogPage","commitId":"57e3cd3c-1bfd-447b-bb06-3bca889d3a9f","commitTimeStamp":"2025-09-05T12:47:02.4666272Z","count":1,"lower":"1.0.0","parent":"https://ky4meru.github.io/RedWine/registration/windows-update/index.json","upper":"1.0.0","items":[{"@id":"https://ky4meru.github.io/RedWine/registration/windows-update/1.0.0.json","@type":"Package","catalogEntry":{"@id":"https://ky4meru.github.io/RedWine/virtualcatalog/data/daf9041f-9967-42af-bbf7-5b4f62c6dec3.json","@type":["PackageDetails","catalog:Permalink"],"authors":"@Ky4meru","dependencyGroups":[],"description":"Automatically install Windows updates","iconUrl":"","id":"windows-update","language":"","licenseUrl":"","listed":true,"packageContent":"https://ky4meru.github.io/RedWine/flatcontainer/windows-update/1.0.0/windows-update.1.0.0.nupkg","projectUrl":"","published":"2025-09-05T12:47:02.3565742Z","requireLicenseAcceptance":false,"summary":"","tags":[],"title":"Windows Update","version":"1.0.0"},"commitId":"57e3cd3c-1bfd-447b-bb06-3bca889d3a9f","commitTimeStamp":"2025-09-05T12:47:02.4663039Z","packageContent":"https://ky4meru.github.io/RedWine/flatcontainer/windows-update/1.0.0/windows-update.1.0.0.nupkg","registration":"https://ky4meru.github.io/RedWine/registration/windows-update/index.json"}]}],"@context":{"@vocab":"http://schema.nuget.org/schema#","catalog":"http://schema.nuget.org/catalog#","xsd":"http://www.w3.org/2001/XMLSchema#","sleet":"http://schema.emgarten.com/sleet#","items":{"@id":"catalog:item","@container":"@set"},"commitTimeStamp":{"@id":"catalog:commitTimeStamp","@type":"xsd:dateTime"},"commitId":{"@id":"catalog:commitId"},"count":{"@id":"catalog:count"},"parent":{"@id":"catalog:parent","@type":"@id"},"tags":{"@container":"@set","@id":"tag"},"packageTargetFrameworks":{"@container":"@set","@id":"packageTargetFramework"},"dependencyGroups":{"@container":"@set","@id":"dependencyGroup"},"dependencies":{"@container":"@set","@id":"dependency"},"packageContent":{"@type":"@id"},"published":{"@type":"xsd:dateTime"},"registration":{"@type":"@id"}}}