{"@id":"https://ky4meru.github.io/RedWine/registration/redwine.godpotato/index.json","@type":["catalog:CatalogRoot","PackageRegistration","catalog:Permalink"],"commitId":"f0ca22ce-30bb-4e84-8b22-c06f601bdaa7","commitTimeStamp":"2025-09-15T11:26:26.3748188Z","count":1,"items":[{"@id":"https://ky4meru.github.io/RedWine/registration/redwine.godpotato/index.json#page/1.20.0/1.20.0","@type":"catalog:CatalogPage","commitId":"f0ca22ce-30bb-4e84-8b22-c06f601bdaa7","commitTimeStamp":"2025-09-15T11:26:26.3749897Z","count":1,"lower":"1.20.0","parent":"https://ky4meru.github.io/RedWine/registration/redwine.godpotato/index.json","upper":"1.20.0","items":[{"@id":"https://ky4meru.github.io/RedWine/registration/redwine.godpotato/1.20.0.json","@type":"Package","catalogEntry":{"@id":"https://ky4meru.github.io/RedWine/virtualcatalog/data/2f279d2d-0f94-4808-9673-3a6ce88bbd41.json","@type":["PackageDetails","catalog:Permalink"],"authors":"@BeichenDream","dependencyGroups":[{"@id":"https://ky4meru.github.io/RedWine/virtualcatalog/data/2f279d2d-0f94-4808-9673-3a6ce88bbd41.json#dependencygroup/any","@type":"PackageDependencyGroup","dependencies":[{"@id":"https://ky4meru.github.io/RedWine/virtualcatalog/data/2f279d2d-0f94-4808-9673-3a6ce88bbd41.json#dependencygroup/any/redwine.extension","@type":"PackageDependency","id":"redwine.extension","range":"(, )"}]}],"description":"Enables privilege escalation in Windows 2012 - Windows 2022, now as long as you have \"ImpersonatePrivilege\" permission","iconUrl":"","id":"redwine.godpotato","language":"","licenseUrl":"","listed":true,"packageContent":"https://ky4meru.github.io/RedWine/flatcontainer/redwine.godpotato/1.20.0/redwine.godpotato.1.20.0.nupkg","projectUrl":"https://github.com/BeichenDream/GodPotato","published":"2025-09-15T11:26:26.2642406Z","requireLicenseAcceptance":false,"summary":"","tags":[],"title":"GodPotato","version":"1.20.0"},"commitId":"f0ca22ce-30bb-4e84-8b22-c06f601bdaa7","commitTimeStamp":"2025-09-15T11:26:26.3746605Z","packageContent":"https://ky4meru.github.io/RedWine/flatcontainer/redwine.godpotato/1.20.0/redwine.godpotato.1.20.0.nupkg","registration":"https://ky4meru.github.io/RedWine/registration/redwine.godpotato/index.json"}]}],"@context":{"@vocab":"http://schema.nuget.org/schema#","catalog":"http://schema.nuget.org/catalog#","xsd":"http://www.w3.org/2001/XMLSchema#","sleet":"http://schema.emgarten.com/sleet#","items":{"@id":"catalog:item","@container":"@set"},"commitTimeStamp":{"@id":"catalog:commitTimeStamp","@type":"xsd:dateTime"},"commitId":{"@id":"catalog:commitId"},"count":{"@id":"catalog:count"},"parent":{"@id":"catalog:parent","@type":"@id"},"tags":{"@container":"@set","@id":"tag"},"packageTargetFrameworks":{"@container":"@set","@id":"packageTargetFramework"},"dependencyGroups":{"@container":"@set","@id":"dependencyGroup"},"dependencies":{"@container":"@set","@id":"dependency"},"packageContent":{"@type":"@id"},"published":{"@type":"xsd:dateTime"},"registration":{"@type":"@id"}}}