{"@id":"https://ky4meru.github.io/RedWine/registration/redwine.krbrelay/index.json","@type":["catalog:CatalogRoot","PackageRegistration","catalog:Permalink"],"commitId":"75f9bdb5-ed8f-4429-b15d-aa9852e3c5b9","commitTimeStamp":"2025-09-10T12:37:36.1561282Z","count":1,"items":[{"@id":"https://ky4meru.github.io/RedWine/registration/redwine.krbrelay/index.json#page/1.0.0/1.0.0","@type":"catalog:CatalogPage","commitId":"75f9bdb5-ed8f-4429-b15d-aa9852e3c5b9","commitTimeStamp":"2025-09-10T12:37:36.1562884Z","count":1,"lower":"1.0.0","parent":"https://ky4meru.github.io/RedWine/registration/redwine.krbrelay/index.json","upper":"1.0.0","items":[{"@id":"https://ky4meru.github.io/RedWine/registration/redwine.krbrelay/1.0.0.json","@type":"Package","catalogEntry":{"@id":"https://ky4meru.github.io/RedWine/virtualcatalog/data/91c2e78f-ebe7-4fd3-aece-7f619326a509.json","@type":["PackageDetails","catalog:Permalink"],"authors":"@cube0x0","dependencyGroups":[{"@id":"https://ky4meru.github.io/RedWine/virtualcatalog/data/91c2e78f-ebe7-4fd3-aece-7f619326a509.json#dependencygroup/any","@type":"PackageDependencyGroup","dependencies":[{"@id":"https://ky4meru.github.io/RedWine/virtualcatalog/data/91c2e78f-ebe7-4fd3-aece-7f619326a509.json#dependencygroup/any/redwine.dotnet-472","@type":"PackageDependency","id":"redwine.dotnet-472","range":"(, )"}]}],"description":"Framework for Kerberos relaying","iconUrl":"","id":"redwine.krbrelay","language":"","licenseUrl":"","listed":true,"packageContent":"https://ky4meru.github.io/RedWine/flatcontainer/redwine.krbrelay/1.0.0/redwine.krbrelay.1.0.0.nupkg","projectUrl":"https://github.com/cube0x0/KrbRelay","published":"2025-09-10T12:37:36.0470535Z","requireLicenseAcceptance":false,"summary":"","tags":[],"title":"KrbRelay","version":"1.0.0"},"commitId":"75f9bdb5-ed8f-4429-b15d-aa9852e3c5b9","commitTimeStamp":"2025-09-10T12:37:36.1559641Z","packageContent":"https://ky4meru.github.io/RedWine/flatcontainer/redwine.krbrelay/1.0.0/redwine.krbrelay.1.0.0.nupkg","registration":"https://ky4meru.github.io/RedWine/registration/redwine.krbrelay/index.json"}]}],"@context":{"@vocab":"http://schema.nuget.org/schema#","catalog":"http://schema.nuget.org/catalog#","xsd":"http://www.w3.org/2001/XMLSchema#","sleet":"http://schema.emgarten.com/sleet#","items":{"@id":"catalog:item","@container":"@set"},"commitTimeStamp":{"@id":"catalog:commitTimeStamp","@type":"xsd:dateTime"},"commitId":{"@id":"catalog:commitId"},"count":{"@id":"catalog:count"},"parent":{"@id":"catalog:parent","@type":"@id"},"tags":{"@container":"@set","@id":"tag"},"packageTargetFrameworks":{"@container":"@set","@id":"packageTargetFramework"},"dependencyGroups":{"@container":"@set","@id":"dependencyGroup"},"dependencies":{"@container":"@set","@id":"dependency"},"packageContent":{"@type":"@id"},"published":{"@type":"xsd:dateTime"},"registration":{"@type":"@id"}}}